Workbook

Sheet Summary
A1: YardSync — NET Profit: Current Product vs. Recommended Additions
A2: Annual NET profit (business cash, before your salary). After all operating costs incl. Claude $200/mo. Driven by the editable Assumptions + Operating Costs tabs.
A4: Scale | B4: CURRENT product | C4: ENHANCED product | D4: Difference (+)
A5: Conservative | B5: =Scenarios!J5 -> 29778 | C5: =Scenarios!J8 -> 114765 | D5: =C5-B5 -> 84987
A6: Base | B6: =Scenarios!J6 -> 61483.5 | C6: =Scenarios!J9 -> 269391 | D6: =C6-B6 -> 207907.5
A7: Optimistic | B7: =Scenarios!J7 -> 109726.5 | C7: =Scenarios!J10 -> 500298 | D7: =C7-B7 -> 390571.5
A8: Figures = recurring annual NET after operating costs. Add one-time Pro Setup income (Scenarios tab) for total Year-1.
A11: THE 3 NUMBERS THAT MATTER
A12: 1. Your real take rate | B12: Direct-charge model: contractor pays Stripe AND your 5.5% separately, so you net the FULL 5.5% of GMV. On $10,000 of invoices that's $550/mo to you.
A13: 2. Where the money is | B13: Mid + Large contractors are ~80%+ of the profit. The current product still loses most of them to fee-flight + missing deposits/quotes/recurring/crew. Winning them is the whole upside.
A14: 3. Biggest risk + cheapest fix | B14: Contractor all-in is ~8.4% and now visible -> high-ticket fee-flight. Cheapest fixes: a 'pass fee to client' toggle, a per-invoice cap, or a low-fee ACH tier. Keep big-job GMV in-platform.
A16: ALREADY SHIPPED (don't re-build)
A17: SMS reminders + AI bilingual drafting · Smart Business Card / QR + social assets · Stripe direct-charge invoicing (5.5%) · contractor-branded receipts · reschedule flows · CSV export (data ownership) · per-client pricing · volume rewards · Terms consent · free-rider gate
A19: WHAT 'ENHANCED' ADDS (Round-2 build order)
A20: P0 Fee strategy: pass-to-client toggle + cap / ACH tier | B20: Cheapest, highest-leverage. Stops high-ticket fee-flight, keeps your full 5.5%.
A21: F14 Quotes/estimates + e-sign + DEPOSITS | B21: Top ask (11 of 13). Stops ghosting, gates high-ticket verticals, deposits = captured GMV.
A22: F20 Recurring auto-billing / contracts | B22: Unlocks pool, HVAC, cleaning, pest, recurring lawn (Jenny, Charlie, Rosa, Dave).
A23: F9 Crew tier (per-seat) — publish a ship date | B23: Only feature that adds a NEW price point; retains growing operators (Diego).
A24: F5 Apple/Google Pay + Stripe Terminal | B24: Faster pay + in-person capture (Marcus, Sasha, Marco).
A25: P0 Stripe Connect onboarding explainer (EN/ES) | B25: Lifts signup-to-first-invoice conversion across the cheap core.

Sheet Assumptions
A1: ASSUMPTIONS — edit the BLUE cells to run your own numbers
A2: Direct-charge model: contractor is merchant of record, pays Stripe separately, so YardSync nets the FULL 5.5%. Fixed costs are itemized on the Operating Costs tab.
A4: YardSync fee (% of each invoice) — net to you | B4: 0.055
A5: Stripe processing % (paid by CONTRACTOR, info) | B5: 0.029
A6: Stripe per-transaction $ (paid by CONTRACTOR, info) | B6: 0.3
A7: Crew tier price / seat / month (Enhanced only) | B7: 15
A8: Pro Setup price (one-time) | B8: 99
A9: Pro Setup labor cost (one-time) | B9: 40
A10: Pro Setup attach rate (% of new signups) | B10: 0.3
A11: Does YardSync absorb the Stripe fee? (1=yes, 0=no) | B11: 0
A13: SEGMENT MODEL ('Other var' = per-contractor infra; build-up on Operating Costs tab)
A14: Segment | B14: GMV / mo | C14: Invoices / mo | D14: Sub $/mo (after rewards) | E14: Support $/mo | F14: Other var $/mo | G14: Crew seats (Enhanced) | H14: Capture % CURRENT | I14: Capture % ENHANCED
A15: Micro (Linda / brand-new) | B15: 1000 | C15: 8 | D15: 39 | E15: 12 | F15: 2.5 | G15: 0 | H15: 0.9 | I15: 0.95
A16: Small (Marco, Joaquin, Tyrell-low) | B16: 2500 | C16: 18 | D16: 19.5 | E16: 8 | F16: 3 | G16: 0 | H16: 0.85 | I16: 0.92
A17: Mid (Rosa, Jenny, Diego) | B17: 10000 | C17: 40 | D17: 0 | E17: 10 | F17: 4 | G17: 1 | H17: 0.6 | I17: 0.9
A18: Large (Dave, Brittany, Sasha, Charlie) | B18: 30000 | C18: 50 | D18: 0 | E18: 15 | F18: 5 | G18: 4 | H18: 0.25 | I18: 0.8
A20: Capture % = share of the contractor's real GMV that flows through YardSync (rest = fee-flight = $0 to you). CURRENT low for Mid/Large; ENHANCED assumes fee strategy + recurring billing + quotes/deposits + crew keep them in.
A21: Contractor's ALL-IN card cost is ~8.4% (your 5.5% + Stripe ~2.9%), now visible to them — the #1 reason high-ticket operators flight to check/ACH.

Sheet Operating Costs
A1: OPERATING COSTS — what it costs to run YardSync
A2: Section A = fixed monthly platform cost (feeds every scenario). Section B = per-contractor usage that justifies the 'Other var' column in Assumptions.
A3: SECTION A — FIXED MONTHLY PLATFORM COST (does NOT scale with # contractors)
A4: Item | B4: $ / month | C4: Note
A5: Anthropic / Claude subscription | B5: 200 | C5: Claude Max — dev + AI features
A6: Vercel Pro (hosting) | B6: 20 | C6: production tier
A7: SendGrid (email) | B7: 20 | C7: Essentials tier
A8: Twilio base (A2P campaign + phone #) | B8: 12 | C8: campaign + number rental, before per-SMS
A9: Firebase Blaze (base / buffer) | B9: 10 | C9: Firestore + Storage baseline at small scale
A10: Domain (amortized) | B10: 1.5 | C10: ~$18/yr
A11: TOTAL FIXED / month | B11: =SUM(B5:B10) -> 263.5 | C11: used as Fixed cost/mo in every scenario
A13: SECTION B — PER-CONTRACTOR USAGE / month (scales with contractors; already in 'Other var')
A14: Cost per SMS (Twilio incl. carrier fee): | B14: 0.012
A15: Segment | B15: SMS / mo | C15: Twilio SMS $ | D15: Firebase $ | E15: AI drafting $ | F15: Stripe on own sub $ | G15: ≈ Total / mo
A16: Micro | B16: 40 | C16: =B16*$B$14 -> 0.48 | D16: 0.3 | E16: 0.1 | F16: =39*Assumptions!$B$5+Assumptions!$B$6 -> 1.431 | G16: =C16+D16+E16+F16 -> 2.311
A17: Small | B17: 90 | C17: =B17*$B$14 -> 1.08 | D17: 0.4 | E17: 0.15 | F17: =19.5*Assumptions!$B$5+Assumptions!$B$6 -> 0.8655 | G17: =C17+D17+E17+F17 -> 2.4955
A18: Mid | B18: 200 | C18: =B18*$B$14 -> 2.4 | D18: 0.6 | E18: 0.2 | F18: =0 -> 0 | G18: =C18+D18+E18+F18 -> 3.2
A19: Large | B19: 320 | C19: =B19*$B$14 -> 3.84 | D19: 0.8 | E19: 0.25 | F19: =0 -> 0 | G19: =C19+D19+E19+F19 -> 4.89
A21: ≈ Total column lines up with the 'Other var $/mo' you can edit in Assumptions (2.5 / 3 / 4 / 5). Twilio/Firebase scale with contractors via this column; the fixed base above stays flat.

Sheet Unit Economics
A1: UNIT ECONOMICS — net profit per contractor per month
A2: YardSync nets the full 5.5% of captured GMV. 'Stripe to platform' is $0 unless you flip the absorb toggle in Assumptions.
A4: CURRENT PRODUCT (live today)
A5: Segment | B5: Captured GMV/mo | C5: Captured inv/mo | D5: YardSync 5.5% fee | E5: Stripe to platform | F5: NET fee | G5: Sub rev | H5: Crew rev | I5: Costs | J5: NET / contractor / mo
A6: =Assumptions!A15 -> Micro (Linda / brand-new) | B6: =Assumptions!B15*Assumptions!H15 -> 900 | C6: =Assumptions!C15*Assumptions!H15 -> 7.2 | D6: =B6*Assumptions!$B$4 -> 49.5 | E6: =Assumptions!$B$11*(B6*Assumptions!$B$5+C6*Assumptions!$B$6) -> 0 | F6: =D6-E6 -> 49.5 | G6: =Assumptions!D15 -> 39 | H6: =0 -> 0 | I6: =Assumptions!E15+Assumptions!F15 -> 14.5 | J6: =F6+G6+H6-I6 -> 74
A7: =Assumptions!A16 -> Small (Marco, Joaquin, Tyrell-low) | B7: =Assumptions!B16*Assumptions!H16 -> 2125 | C7: =Assumptions!C16*Assumptions!H16 -> 15.3 | D7: =B7*Assumptions!$B$4 -> 116.875 | E7: =Assumptions!$B$11*(B7*Assumptions!$B$5+C7*Assumptions!$B$6) -> 0 | F7: =D7-E7 -> 116.875 | G7: =Assumptions!D16 -> 19.5 | H7: =0 -> 0 | I7: =Assumptions!E16+Assumptions!F16 -> 11 | J7: =F7+G7+H7-I7 -> 125.375
A8: =Assumptions!A17 -> Mid (Rosa, Jenny, Diego) | B8: =Assumptions!B17*Assumptions!H17 -> 6000 | C8: =Assumptions!C17*Assumptions!H17 -> 24 | D8: =B8*Assumptions!$B$4 -> 330 | E8: =Assumptions!$B$11*(B8*Assumptions!$B$5+C8*Assumptions!$B$6) -> 0 | F8: =D8-E8 -> 330 | G8: =Assumptions!D17 -> 0 | H8: =0 -> 0 | I8: =Assumptions!E17+Assumptions!F17 -> 14 | J8: =F8+G8+H8-I8 -> 316
A9: =Assumptions!A18 -> Large (Dave, Brittany, Sasha, Charlie) | B9: =Assumptions!B18*Assumptions!H18 -> 7500 | C9: =Assumptions!C18*Assumptions!H18 -> 12.5 | D9: =B9*Assumptions!$B$4 -> 412.5 | E9: =Assumptions!$B$11*(B9*Assumptions!$B$5+C9*Assumptions!$B$6) -> 0 | F9: =D9-E9 -> 412.5 | G9: =Assumptions!D18 -> 0 | H9: =0 -> 0 | I9: =Assumptions!E18+Assumptions!F18 -> 20 | J9: =F9+G9+H9-I9 -> 392.5
A11: ENHANCED PRODUCT (+ deposits/quotes, recurring billing, crew, fee strategy)
A12: Segment | B12: Captured GMV/mo | C12: Captured inv/mo | D12: YardSync 5.5% fee | E12: Stripe to platform | F12: NET fee | G12: Sub rev | H12: Crew rev | I12: Costs | J12: NET / contractor / mo
A13: =Assumptions!A15 -> Micro (Linda / brand-new) | B13: =Assumptions!B15*Assumptions!I15 -> 950 | C13: =Assumptions!C15*Assumptions!I15 -> 7.6 | D13: =B13*Assumptions!$B$4 -> 52.25 | E13: =Assumptions!$B$11*(B13*Assumptions!$B$5+C13*Assumptions!$B$6) -> 0 | F13: =D13-E13 -> 52.25 | G13: =Assumptions!D15 -> 39 | H13: =Assumptions!G15*Assumptions!$B$7 -> 0 | I13: =Assumptions!E15+Assumptions!F15 -> 14.5 | J13: =F13+G13+H13-I13 -> 76.75
A14: =Assumptions!A16 -> Small (Marco, Joaquin, Tyrell-low) | B14: =Assumptions!B16*Assumptions!I16 -> 2300 | C14: =Assumptions!C16*Assumptions!I16 -> 16.56 | D14: =B14*Assumptions!$B$4 -> 126.5 | E14: =Assumptions!$B$11*(B14*Assumptions!$B$5+C14*Assumptions!$B$6) -> 0 | F14: =D14-E14 -> 126.5 | G14: =Assumptions!D16 -> 19.5 | H14: =Assumptions!G16*Assumptions!$B$7 -> 0 | I14: =Assumptions!E16+Assumptions!F16 -> 11 | J14: =F14+G14+H14-I14 -> 135
A15: =Assumptions!A17 -> Mid (Rosa, Jenny, Diego) | B15: =Assumptions!B17*Assumptions!I17 -> 9000 | C15: =Assumptions!C17*Assumptions!I17 -> 36 | D15: =B15*Assumptions!$B$4 -> 495 | E15: =Assumptions!$B$11*(B15*Assumptions!$B$5+C15*Assumptions!$B$6) -> 0 | F15: =D15-E15 -> 495 | G15: =Assumptions!D17 -> 0 | H15: =Assumptions!G17*Assumptions!$B$7 -> 15 | I15: =Assumptions!E17+Assumptions!F17 -> 14 | J15: =F15+G15+H15-I15 -> 496
A16: =Assumptions!A18 -> Large (Dave, Brittany, Sasha, Charlie) | B16: =Assumptions!B18*Assumptions!I18 -> 24000 | C16: =Assumptions!C18*Assumptions!I18 -> 40 | D16: =B16*Assumptions!$B$4 -> 1320 | E16: =Assumptions!$B$11*(B16*Assumptions!$B$5+C16*Assumptions!$B$6) -> 0 | F16: =D16-E16 -> 1320 | G16: =Assumptions!D18 -> 0 | H16: =Assumptions!G18*Assumptions!$B$7 -> 60 | I16: =Assumptions!E18+Assumptions!F18 -> 20 | J16: =F16+G16+H16-I16 -> 1360

Sheet Scenarios
A1: SCENARIOS — portfolio of active contractors → NET profit / year
A2: Blue = contractor counts you can change. Fixed cost/mo pulls from the Operating Costs tab (incl. Claude $200).
A4: Product | B4: Scale | C4: Micro # | D4: Small # | E4: Mid # | F4: Large # | G4: Contractor net/mo | H4: Fixed cost/mo | I4: NET / mo | J4: NET / yr (recurring) | K4: Pro Setup (yr) | L4: TOTAL Year-1 NET
A5: Current | B5: Conservative | C5: 15 | D5: 8 | E5: 2 | F5: 0 | G5: =C5*'Unit Economics'!$J$6+D5*'Unit Economics'!$J$7+E5*'Unit Economics'!$J$8+F5*'Unit Economics'!$J$9 -> 2745 | H5: ='Operating Costs'!$B$11 -> 263.5 | I5: =G5-H5 -> 2481.5 | J5: =I5*12 -> 29778 | K5: =(C5+D5+E5+F5)*Assumptions!$B$10*(Assumptions!$B$8-Assumptions!$B$9) -> 442.5 | L5: =J5+K5 -> 30220.5
A6: Current | B6: Base | C6: 25 | D6: 15 | E6: 4 | F6: 1 | G6: =C6*'Unit Economics'!$J$6+D6*'Unit Economics'!$J$7+E6*'Unit Economics'!$J$8+F6*'Unit Economics'!$J$9 -> 5387.125 | H6: ='Operating Costs'!$B$11 -> 263.5 | I6: =G6-H6 -> 5123.625 | J6: =I6*12 -> 61483.5 | K6: =(C6+D6+E6+F6)*Assumptions!$B$10*(Assumptions!$B$8-Assumptions!$B$9) -> 796.5 | L6: =J6+K6 -> 62280
A7: Current | B7: Optimistic | C7: 40 | D7: 25 | E7: 8 | F7: 2 | G7: =C7*'Unit Economics'!$J$6+D7*'Unit Economics'!$J$7+E7*'Unit Economics'!$J$8+F7*'Unit Economics'!$J$9 -> 9407.375 | H7: ='Operating Costs'!$B$11 -> 263.5 | I7: =G7-H7 -> 9143.875 | J7: =I7*12 -> 109726.5 | K7: =(C7+D7+E7+F7)*Assumptions!$B$10*(Assumptions!$B$8-Assumptions!$B$9) -> 1327.5 | L7: =J7+K7 -> 111054
A8: Enhanced | B8: Conservative | C8: 15 | D8: 12 | E8: 6 | F8: 3 | G8: =C8*'Unit Economics'!$J$13+D8*'Unit Economics'!$J$14+E8*'Unit Economics'!$J$15+F8*'Unit Economics'!$J$16 -> 9827.25 | H8: ='Operating Costs'!$B$11 -> 263.5 | I8: =G8-H8 -> 9563.75 | J8: =I8*12 -> 114765 | K8: =(C8+D8+E8+F8)*Assumptions!$B$10*(Assumptions!$B$8-Assumptions!$B$9) -> 637.2 | L8: =J8+K8 -> 115402.2
A9: Enhanced | B9: Base | C9: 25 | D9: 22 | E9: 14 | F9: 8 | G9: =C9*'Unit Economics'!$J$13+D9*'Unit Economics'!$J$14+E9*'Unit Economics'!$J$15+F9*'Unit Economics'!$J$16 -> 22712.75 | H9: ='Operating Costs'!$B$11 -> 263.5 | I9: =G9-H9 -> 22449.25 | J9: =I9*12 -> 269391 | K9: =(C9+D9+E9+F9)*Assumptions!$B$10*(Assumptions!$B$8-Assumptions!$B$9) -> 1221.3 | L9: =J9+K9 -> 270612.3
A10: Enhanced | B10: Optimistic | C10: 40 | D10: 35 | E10: 25 | F10: 16 | G10: =C10*'Unit Economics'!$J$13+D10*'Unit Economics'!$J$14+E10*'Unit Economics'!$J$15+F10*'Unit Economics'!$J$16 -> 41955 | H10: ='Operating Costs'!$B$11 -> 263.5 | I10: =G10-H10 -> 41691.5 | J10: =I10*12 -> 500298 | K10: =(C10+D10+E10+F10)*Assumptions!$B$10*(Assumptions!$B$8-Assumptions!$B$9) -> 2053.2 | L10: =J10+K10 -> 502351.2
